Metadata-Version: 2.1
Name: biops
Version: 0.2.1
Summary: Bioprocess simulator
Home-page: https://github.com/omvatten/biops/
Author: Oskar Modin
Author-email: omvatten@gmail.com
License: UNKNOWN
Platform: UNKNOWN
Classifier: Programming Language :: Python :: 3.9
Classifier: License :: OSI Approved :: GNU General Public License v3 (GPLv3)
